driftimpact/__init__.py
driftimpact/advisor.py
driftimpact/analyzer.py
driftimpact/concept_drift.py
driftimpact/concept_drift_visualization.py
driftimpact/drift_detection.py
driftimpact/drift_visualization.py
driftimpact/html_report.py
driftimpact/metrics.py
driftimpact/performance_impact.py
driftimpact-1.1.0.dist-info/METADATA
driftimpact-1.1.0.dist-info/WHEEL
driftimpact-1.1.0.dist-info/top_level.txt
driftimpact-1.1.0.dist-info/RECORD
