Metadata-Version: 2.4
Name: driftimpact
Version: 1.1.0
Summary: A comprehensive library for data and concept drift detection with performance impact analysis
Home-page: https://github.com/serkanars/driftimpact
Author: Serkan Arslan
Author-email: arslanserkan0@gmail.com
Requires-Python: >=3.7
Requires-Dist: pandas
Requires-Dist: numpy
Requires-Dist: scipy
Requires-Dist: matplotlib
Requires-Dist: seaborn
Requires-Dist: tabulate
Requires-Dist: scikit-learn
Requires-Dist: requests
Dynamic: author
Dynamic: author-email
Dynamic: description
Dynamic: description-content-type
Dynamic: home-page
Dynamic: requires-dist
Dynamic: requires-python
Dynamic: summary
